{
  "publicPath": "/_nuxt/",
  "all": [
    "../server/index.spa.html",
    "../server/index.ssr.html",
    "0dad5a7.js",
    "13e6946.js",
    "161288b.js",
    "1cff849.js",
    "1d20270.js",
    "1d9def6.js",
    "2bb6025.js",
    "32ec95a.js",
    "3754c56.js",
    "3a6d18b.js",
    "3b0361c.js",
    "3e10c1d.js",
    "3f92b4e.js",
    "437abfe.js",
    "441edb3.js",
    "4429295.js",
    "47aa85a.js",
    "47d267d.js",
    "4ae27bd.js",
    "4d7dea9.js",
    "4f18cd2.js",
    "51bf4b4.js",
    "57cddbb.js",
    "677be11.js",
    "7470bf5.js",
    "756caf6.js",
    "769ef96.js",
    "7c90b3c.js",
    "80c9862.js",
    "87346c0.js",
    "8f403d4.js",
    "966c4af.js",
    "9866687.js",
    "LICENSES",
    "a69b2f3.js",
    "ab74a57.js",
    "c4ffe79.js",
    "dab7934.js",
    "e1c59ab.js",
    "f4ff530.js",
    "f6d9ca7.js",
    "fea7a24.js",
    "fffdfaa.js"
  ],
  "initial": [
    "161288b.js",
    "4429295.js",
    "966c4af.js",
    "8f403d4.js"
  ],
  "async": [
    "0dad5a7.js",
    "13e6946.js",
    "1cff849.js",
    "1d20270.js",
    "1d9def6.js",
    "2bb6025.js",
    "32ec95a.js",
    "3754c56.js",
    "3a6d18b.js",
    "3b0361c.js",
    "3e10c1d.js",
    "3f92b4e.js",
    "437abfe.js",
    "441edb3.js",
    "47aa85a.js",
    "47d267d.js",
    "4ae27bd.js",
    "4d7dea9.js",
    "4f18cd2.js",
    "51bf4b4.js",
    "57cddbb.js",
    "677be11.js",
    "7470bf5.js",
    "756caf6.js",
    "769ef96.js",
    "7c90b3c.js",
    "80c9862.js",
    "87346c0.js",
    "9866687.js",
    "a69b2f3.js",
    "ab74a57.js",
    "c4ffe79.js",
    "dab7934.js",
    "e1c59ab.js",
    "f4ff530.js",
    "f6d9ca7.js",
    "fea7a24.js",
    "fffdfaa.js"
  ],
  "modules": {
    "25885464": [
      12
    ],
    "29828383": [
      17
    ],
    "32809873": [
      17
    ],
    "39073771": [
      20
    ],
    "44486771": [
      17
    ],
    "46187903": [
      33
    ],
    "48520666": [
      17
    ],
    "63905361": [
      33
    ],
    "69832575": [
      33
    ],
    "72116054": [
      39
    ],
    "72442794": [
      17
    ],
    "74757329": [
      18
    ],
    "75199091": [
      42
    ],
    "75581922": [
      17
    ],
    "76020852": [
      9
    ],
    "78705215": [
      17
    ],
    "4c0bc5e6": [
      17
    ],
    "4c94912a": [
      32
    ],
    "5f50c26d": [
      33
    ],
    "1223242e": [
      33
    ],
    "43d274f0": [
      17
    ],
    "fd923f46": [
      17
    ],
    "750c1300": [
      17
    ],
    "47edc98e": [
      17
    ],
    "48d13365": [
      33
    ],
    "acfe7a24": [
      33
    ],
    "64a87512": [
      17
    ],
    "fe25b11e": [
      17
    ],
    "1d01eaec": [
      33
    ],
    "4f1630e9": [
      17
    ],
    "da102824": [
      17
    ],
    "50d8b67f": [
      17
    ],
    "d2ea47c8": [
      33
    ],
    "02521f6c": [
      17
    ],
    "29d00e8a": [
      17
    ],
    "bd76ab98": [
      17
    ],
    "5d1940e0": [
      17
    ],
    "2d8c508d": [
      17
    ],
    "2003e98f": [
      17
    ],
    "f8792b72": [
      17
    ],
    "166f4b58": [
      17
    ],
    "1eb7ae97": [
      17
    ],
    "a922925a": [
      17
    ],
    "c0c28daa": [
      33
    ],
    "d1d45d96": [
      33
    ],
    "ce21d0be": [
      33
    ],
    "684d2de8": [
      33
    ],
    "464ae556": [
      33
    ],
    "f369dee2": [
      33
    ],
    "bf5dedd0": [
      17
    ],
    "3f156128": [
      17
    ],
    "3c87171e": [
      17
    ],
    "06be3d8c": [
      17
    ],
    "e8f98ea8": [
      17
    ],
    "20ad57a6": [
      17
    ],
    "4ab90992": [
      17
    ],
    "05722a03": [
      17
    ],
    "0d8dfe49": [
      33
    ],
    "5afaa0be": [
      17
    ],
    "7d780cbc": [
      17
    ],
    "7da93c62": [
      17
    ],
    "1cfca022": [
      17
    ],
    "48ac7fc1": [
      17
    ],
    "27b0c8c5": [
      17
    ],
    "d9a0929e": [
      17
    ],
    "c1620fd0": [
      17
    ],
    "070e1e4a": [
      17
    ],
    "7816bf43": [
      17
    ],
    "97a07066": [
      33
    ],
    "9c28fb30": [
      17
    ],
    "594f145a": [
      17
    ],
    "1a79a3a9": [
      17
    ],
    "aa0e127e": [
      17
    ],
    "4fa181d0": [
      17
    ],
    "475b31f0": [
      17
    ],
    "0568f79b": [
      17
    ],
    "b44586f4": [
      17
    ],
    "23734a91": [
      33
    ],
    "52b83dfb": [
      17
    ],
    "27b87969": [
      32
    ],
    "0994b10a": [
      32
    ],
    "49c51223": [
      32
    ],
    "0d4d0f86": [
      32
    ],
    "572b79d2": [
      32
    ],
    "cdf8224c": [
      32
    ],
    "0a312c22": [
      32
    ],
    "4d8e59dc": [
      32
    ],
    "380ce27b": [
      32
    ],
    "bab8ab98": [
      32
    ],
    "68b68112": [
      32
    ],
    "52f00ab8": [
      32
    ],
    "c945e2be": [
      32
    ],
    "7f335a31": [
      32
    ],
    "53e0ac5c": [
      32
    ],
    "1c829432": [
      32
    ],
    "921e99aa": [
      32
    ],
    "98b81990": [
      32
    ],
    "10c39a67": [
      32
    ],
    "0b127056": [
      32
    ],
    "0feb0788": [
      32
    ],
    "deef6494": [
      32
    ],
    "9f2d0bca": [
      32
    ],
    "bcf09a60": [
      32
    ],
    "b6845b08": [
      32
    ],
    "7488981b": [
      17
    ],
    "7ee27bfc": [
      17
    ],
    "0f300f64": [
      17
    ],
    "244288c5": [
      17
    ],
    "05ff33ab": [
      17
    ],
    "585ef87e": [
      17
    ],
    "044467c5": [
      17
    ],
    "21093dfc": [
      17
    ],
    "2b71f484": [
      17
    ],
    "7efd456c": [
      33
    ],
    "2cd11786": [
      33
    ],
    "5de1a329": [
      17
    ],
    "5cd2a2b6": [
      17
    ],
    "21c507a8": [
      17
    ],
    "43c89df8": [
      17
    ],
    "5cb138b3": [
      17
    ],
    "98a182a6": [
      17
    ],
    "4bddc774": [
      17
    ],
    "c76116f2": [
      17
    ],
    "66a4a337": [
      17
    ],
    "70eebe42": [
      17
    ],
    "5c99aee1": [
      17
    ],
    "2545a29a": [
      17
    ],
    "51eefd66": [
      17
    ],
    "0cadcb14": [
      17
    ],
    "37f6d3a4": [
      17
    ],
    "3945fc46": [
      17
    ],
    "765f1e74": [
      17
    ],
    "e295e6fc": [
      17
    ],
    "3e6d8df0": [
      33
    ],
    "03cdcbc8": [
      33
    ],
    "05c3acb6": [
      33
    ],
    "1a3dea20": [
      33
    ],
    "0c92d63f": [
      33
    ],
    "384b1b92": [
      33
    ],
    "599d8f42": [
      33
    ],
    "733428f3": [
      17
    ],
    "1ecbcec9": [
      17
    ],
    "1ea28724": [
      17
    ],
    "33478aec": [
      17
    ],
    "4d766d1a": [
      17
    ],
    "11f9c297": [
      17
    ],
    "526f9650": [
      17
    ],
    "56ddf5bb": [
      17
    ],
    "4e36a42d": [
      17
    ],
    "d26fa99c": [
      17
    ],
    "f5505c94": [
      17
    ],
    "702fd1ba": [
      17
    ],
    "1aedd0e3": [
      17
    ],
    "2686595c": [
      17
    ],
    "04e87e05": [
      17
    ],
    "6ff17418": [
      17
    ],
    "e73696c0": [
      17
    ],
    "e6222ae8": [
      17
    ],
    "1ab55eee": [
      17
    ],
    "60ee63b7": [
      33
    ],
    "6447b67a": [
      33
    ],
    "489b8d4d": [
      33
    ],
    "656c98f1": [
      33
    ],
    "7a494f70": [
      33
    ],
    "62a6923e": [
      33
    ],
    "3e7e2e67": [
      33
    ],
    "7fd6ee13": [
      33
    ],
    "5dbba098": [
      33
    ],
    "686b7fd0": [
      33
    ],
    "00d31cda": [
      33
    ],
    "04c2a7c5": [
      33
    ],
    "898127f4": [
      33
    ],
    "fee8cda8": [
      33
    ],
    "2ce68caa": [
      33
    ],
    "77faf93c": [
      33
    ],
    "7a2f4c62": [
      33
    ],
    "fad08f4e": [
      33
    ],
    "2fe535fb": [
      33
    ],
    "4b6ec63e": [
      33
    ],
    "6e6cf634": [
      33
    ],
    "212788f8": [
      33
    ],
    "05bb3756": [
      33
    ],
    "9c74b922": [
      33
    ],
    "055735b2": [
      33
    ],
    "b4dd4e30": [
      33
    ],
    "515041bb": [
      33
    ],
    "0c17385c": [
      33
    ],
    "78c3fdac": [
      33
    ],
    "ba84397e": [
      17
    ],
    "073ec602": [
      17
    ],
    "3697d595": [
      17
    ],
    "be2fa078": [
      17
    ],
    "3ce33ee5": [
      17
    ],
    "d5a15f5e": [
      17
    ],
    "3d8cb143": [
      17
    ],
    "59fc18c7": [
      17
    ],
    "c78c737c": [
      17
    ],
    "5c290afd": [
      17
    ],
    "6f992585": [
      17
    ],
    "f4c3e9ee": [
      17
    ],
    "ceae668a": [
      17
    ],
    "41a919f6": [
      17
    ],
    "9e1b32bc": [
      17
    ],
    "2d473df6": [
      17
    ],
    "f51edb46": [
      17
    ],
    "0cc5c469": [
      33
    ],
    "2e7753de": [
      33
    ],
    "5d38f1d2": [
      33
    ],
    "e7fee520": [
      33
    ],
    "193bd658": [
      33
    ],
    "8c792e58": [
      33
    ],
    "422394e2": [
      33
    ],
    "50493c65": [
      33
    ],
    "6c8fc7e6": [
      33
    ],
    "293d9822": [
      33
    ],
    "cacb03c0": [
      32
    ],
    "13422f84": [
      17
    ],
    "477ef43a": [
      17
    ],
    "3d9897ef": [
      17
    ],
    "a6806e8e": [
      17
    ],
    "c2eda20e": [
      17
    ],
    "d65d84d0": [
      17
    ],
    "19dcea48": [
      17
    ],
    "200591aa": [
      17
    ],
    "d80c6792": [
      17
    ],
    "6ba804e1": [
      17
    ],
    "21ab5e6e": [
      17
    ],
    "f9681640": [
      17
    ],
    "8843011c": [
      17
    ],
    "2e9b427e": [
      17
    ],
    "5160d7d1": [
      17
    ],
    "5bc486d7": [
      17
    ],
    "0ff4c8b8": [
      17
    ],
    "6f40179a": [
      17
    ],
    "4757365d": [
      17
    ],
    "41663ce6": [
      17
    ],
    "bd815c26": [
      17
    ],
    "613ea498": [
      17
    ],
    "b39bf930": [
      17
    ],
    "ae7c5696": [
      17
    ],
    "6c12c1db": [
      17
    ],
    "45eef14e": [
      17
    ],
    "588049e4": [
      17
    ],
    "2c77337a": [
      33
    ],
    "9df832d2": [
      32
    ],
    "f27df57c": [
      32
    ],
    "746a3254": [
      32
    ],
    "e05cfab6": [
      32
    ],
    "0062c826": [
      32
    ],
    "3f6ca9ba": [
      32
    ],
    "3281240b": [
      33
    ],
    "1fd0c900": [
      33
    ],
    "7c559db5": [
      33
    ],
    "a4867fbe": [
      32
    ],
    "17d348d4": [
      33
    ],
    "2acd2508": [
      17
    ],
    "5ae22c33": [
      33
    ],
    "6e762c45": [
      33
    ],
    "3ed13454": [
      33
    ],
    "51012b37": [
      33
    ],
    "18b5f364": [
      17
    ],
    "594c59a5": [
      17
    ],
    "b190430c": [
      17
    ],
    "64bb4636": [
      17
    ],
    "2e8369c7": [
      17
    ],
    "d635c2c6": [
      17
    ],
    "08c981df": [
      17
    ],
    "e8e4e758": [
      17
    ],
    "17ca52c1": [
      17
    ],
    "75ccc42c": [
      17
    ],
    "708edcb5": [
      17
    ],
    "2e19e344": [
      17
    ],
    "c2099952": [
      17
    ],
    "4f1c939d": [
      17
    ],
    "99fb20f2": [
      17
    ],
    "138582e1": [
      17
    ],
    "7abc7642": [
      17
    ],
    "b77f5ada": [
      17
    ],
    "a903b37a": [
      17
    ],
    "27d13912": [
      17
    ],
    "0fc2a658": [
      17
    ],
    "33b18e60": [
      17
    ],
    "b0f62a8e": [
      17
    ],
    "38c30bd6": [
      17
    ],
    "6921fe92": [
      17
    ],
    "4ed69288": [
      17
    ],
    "ebad1b4e": [
      17
    ],
    "711f7cdb": [
      17
    ],
    "6df50b06": [
      17
    ],
    "dc260b20": [
      17
    ],
    "28579d86": [
      17
    ],
    "906ff352": [
      17
    ],
    "0fb0f35c": [
      17
    ],
    "1a903c8a": [
      17
    ],
    "798e38dc": [
      17
    ],
    "57e71c5d": [
      17
    ],
    "1165ff4a": [
      17
    ],
    "097d02e8": [
      17
    ],
    "481ba52c": [
      17
    ],
    "015dc763": [
      17
    ],
    "2e5319cf": [
      17
    ],
    "3161256a": [
      17
    ],
    "45febad6": [
      17
    ],
    "194e4434": [
      17
    ],
    "18e037fc": [
      17
    ],
    "72462d78": [
      32
    ],
    "047a5520": [
      32
    ],
    "708e8fd1": [
      17
    ],
    "8e49bb30": [
      17
    ],
    "0bdc3fc3": [
      17
    ],
    "5c21051e": [
      17
    ],
    "2e8ed9aa": [
      17
    ],
    "46fc8a89": [
      17
    ],
    "5519a592": [
      17
    ],
    "0e7520b7": [
      17
    ],
    "a91e9406": [
      17
    ],
    "39a5b906": [
      17
    ],
    "3abdb1e2": [
      17
    ],
    "b98c4998": [
      17
    ],
    "46bf7e08": [
      17
    ],
    "00dcfd6e": [
      17
    ],
    "222dc28e": [
      17
    ],
    "bee73c34": [
      33
    ],
    "216af547": [
      17
    ],
    "94e0d85a": [
      17
    ],
    "fbcaa098": [
      17
    ],
    "9800316c": [
      17
    ],
    "0c3582dc": [
      17
    ],
    "26507cc5": [
      33
    ],
    "063bc602": [
      33
    ],
    "cdc8780c": [
      33
    ],
    "7de89b44": [
      33
    ],
    "37ef898a": [
      17
    ],
    "447dbed2": [
      32
    ],
    "6b3e9956": [
      33
    ],
    "f8f48d8e": [
      33
    ],
    "4c439802": [
      33
    ],
    "87ee447a": [
      33
    ],
    "d1aec6c2": [
      33
    ],
    "6f1ed447": [
      33
    ],
    "9dbe14da": [
      17
    ],
    "2601bea0": [
      17
    ],
    "e7b0e920": [
      17
    ],
    "b1a22652": [
      17
    ],
    "1821cac3": [
      32
    ],
    "7717bfcc": [
      33
    ],
    "e3ea2570": [
      32
    ],
    "4a0ea872": [
      17
    ],
    "54be3335": [
      17
    ],
    "7402b31c": [
      17
    ],
    "0e494e7a": [
      17
    ],
    "43ce991a": [
      17
    ],
    "4961d30a": [
      17
    ],
    "ce7e94ae": [
      17
    ],
    "964db69c": [
      17
    ],
    "384869a6": [
      17
    ],
    "95e48dae": [
      17
    ],
    "7fbf7016": [
      17
    ],
    "7672a4ed": [
      17
    ],
    "7f5a971d": [
      17
    ],
    "14f7c522": [
      17
    ],
    "d431e8c2": [
      17
    ],
    "52c03205": [
      17
    ],
    "d1cf5886": [
      17
    ],
    "47111e6f": [
      17
    ],
    "628b7ef4": [
      17
    ],
    "e34e2022": [
      17
    ],
    "0d359e35": [
      17
    ],
    "53aafbfd": [
      17
    ],
    "7d0c4946": [
      17
    ],
    "984f9e6c": [
      17
    ],
    "6afb6b06": [
      17
    ],
    "7e7a602e": [
      17
    ],
    "d9ff7948": [
      17
    ],
    "b7e8fcc8": [
      17
    ],
    "5fe95f63": [
      17
    ],
    "32a8c87d": [
      17
    ],
    "f2bd9044": [
      17
    ],
    "ca429242": [
      17
    ],
    "22993e72": [
      17
    ],
    "d314feba": [
      17
    ],
    "437cee6f": [
      17
    ],
    "71c51b36": [
      17
    ],
    "6f974300": [
      17
    ],
    "7433c7cc": [
      17
    ],
    "3f170436": [
      17
    ],
    "068496e8": [
      17
    ],
    "3a337db2": [
      17
    ],
    "097bcee5": [
      17
    ],
    "bacf882a": [
      17
    ],
    "0261536c": [
      17
    ],
    "83f7b292": [
      17
    ],
    "5972f18e": [
      17
    ],
    "2129cc82": [
      17
    ],
    "4649da04": [
      17
    ],
    "6fffed4b": [
      32
    ],
    "ba1726c6": [
      32
    ],
    "2b961892": [
      32
    ],
    "3206e689": [
      32
    ],
    "b0504960": [
      32
    ],
    "bef37252": [
      32
    ],
    "1d220fc6": [
      33
    ],
    "6fafc9dc": [
      33
    ],
    "9bd9c376": [
      17
    ],
    "77c0dfde": [
      17
    ],
    "55b8c4e8": [
      17
    ],
    "c23d47c4": [
      17
    ],
    "f06e7aa8": [
      17
    ],
    "32f98437": [
      17
    ],
    "ff6cd2b2": [
      17
    ],
    "f2d82308": [
      33
    ],
    "9def2cee": [
      17
    ],
    "771adf65": [
      17
    ],
    "6b4eaf8e": [
      17
    ],
    "719c87c8": [
      17
    ],
    "ef5b8364": [
      17
    ],
    "10e6a09a": [
      17
    ],
    "091911a6": [
      17
    ],
    "9623d3d8": [
      17
    ],
    "24036e07": [
      17
    ],
    "4111ee52": [
      33
    ],
    "27197ae8": [
      33
    ],
    "5540e80e": [
      33
    ],
    "0cab64b8": [
      33
    ],
    "29b1cc40": [
      17
    ],
    "78804bae": [
      33
    ],
    "939b615a": [
      33
    ],
    "c5fd228a": [
      17
    ],
    "ef5d8a74": [
      17
    ],
    "3a66d196": [
      17
    ],
    "76c1ecaa": [
      33
    ],
    "3f431054": [
      33
    ],
    "009d0ec6": [
      33
    ],
    "fa186448": [
      33
    ],
    "467b4d06": [
      33
    ],
    "3290911c": [
      33
    ],
    "61d3baf4": [
      33
    ],
    "21a3dc9c": [
      33
    ],
    "4ef14b8a": [
      33
    ],
    "6a66b1c0": [
      33
    ],
    "80a187c6": [
      33
    ],
    "b4926e9a": [
      33
    ],
    "38b2aee6": [
      33
    ],
    "e97f2e08": [
      33
    ],
    "2901f59a": [
      33
    ],
    "0872a030": [
      33
    ],
    "047927e2": [
      33
    ],
    "0596bb35": [
      33
    ],
    "8cd0413e": [
      33
    ],
    "571cffcb": [
      33
    ],
    "1aaf1b03": [
      33
    ],
    "1a53a7eb": [
      33
    ],
    "00b5f685": [
      33
    ],
    "77a8f97d": [
      33
    ],
    "5a1d0223": [
      33
    ],
    "68e0c832": [
      33
    ],
    "1e2f2af2": [
      33
    ],
    "4c855f57": [
      33
    ],
    "061403c8": [
      22
    ],
    "3bedc32c": [
      39
    ],
    "42d2ab6c": [
      39
    ],
    "8860bca4": [
      39
    ],
    "64824f34": [
      39
    ],
    "66c8217c": [
      39
    ],
    "5d141980": [
      39
    ],
    "431ba616": [
      39
    ],
    "65360dba": [
      22
    ],
    "a2222b16": [
      22
    ],
    "21317b93": [
      39
    ],
    "0d3be8fa": [
      39
    ],
    "2f5ee8a3": [
      39
    ],
    "0611e5da": [
      39
    ],
    "1692a033": [
      39
    ],
    "fc05be08": [
      39
    ],
    "9ddaea86": [
      39
    ],
    "92eccc4a": [
      39
    ],
    "014873a1": [
      2
    ],
    "0735d4f1": [
      2
    ],
    "35ad785f": [
      2
    ],
    "0cad7bdd": [
      2
    ],
    "ac1d7a4e": [
      2
    ],
    "645782e2": [
      41
    ],
    "1170258b": [
      41
    ],
    "103c648d": [
      41
    ],
    "cf86d112": [
      41
    ],
    "53f6f4f2": [
      41
    ],
    "c1dba89a": [
      40
    ],
    "436414fb": [
      40
    ],
    "32b94d52": [
      40
    ],
    "d3b43ee2": [
      40
    ],
    "4c4150c6": [
      40
    ],
    "e56d131a": [
      13
    ],
    "1edc4569": [
      13
    ],
    "7a566417": [
      13
    ],
    "719e10fd": [
      13
    ],
    "6d92625d": [
      13
    ],
    "55a2571e": [
      7
    ],
    "44e53a60": [
      7
    ],
    "59cf4faf": [
      7
    ],
    "bc859168": [
      7
    ],
    "898131ae": [
      7
    ],
    "48e7170a": [
      25
    ],
    "4490ce6d": [
      25
    ],
    "6829d6df": [
      25
    ],
    "fa8f21fe": [
      25
    ],
    "34bcaea5": [
      25
    ],
    "4162fbc7": [
      19
    ],
    "e35528ea": [
      19
    ],
    "851b5eaa": [
      19
    ],
    "37d2a21f": [
      19
    ],
    "5cb0551e": [
      19
    ],
    "7f424d7a": [
      12
    ],
    "04edb8ad": [
      12
    ],
    "324c561e": [
      12
    ],
    "57af8441": [
      12
    ],
    "001b7fa0": [
      38
    ],
    "946d44c4": [
      38
    ],
    "9e75d8d8": [
      38
    ],
    "181e039c": [
      38
    ],
    "7d57eb5a": [
      38
    ],
    "ad04d7a8": [
      14
    ],
    "7f734107": [
      14
    ],
    "3cd94e6a": [
      14
    ],
    "4769841a": [
      14
    ],
    "c36d3438": [
      14
    ],
    "7c96562a": [
      31
    ],
    "f56450ec": [
      31
    ],
    "dea84ae2": [
      31
    ],
    "4fe0b9c4": [
      31
    ],
    "f8304e56": [
      31
    ],
    "6cf01466": [
      6
    ],
    "54dfcb55": [
      6
    ],
    "6dadc1cb": [
      6
    ],
    "48a7857e": [
      6
    ],
    "3375e2c5": [
      6
    ],
    "79a46586": [
      29
    ],
    "e01da7b8": [
      29
    ],
    "5e5da021": [
      29
    ],
    "396e62b8": [
      29
    ],
    "729324e7": [
      29
    ],
    "59e27c30": [
      28
    ],
    "538ffd4f": [
      28
    ],
    "50712b24": [
      28
    ],
    "9f300b8a": [
      28
    ],
    "393781e8": [
      28
    ],
    "cb581dd0": [
      37
    ],
    "316ceca3": [
      37
    ],
    "783ab154": [
      37
    ],
    "e3762ce2": [
      37
    ],
    "2552bed0": [
      37
    ],
    "e9c49bbe": [
      21
    ],
    "5b195830": [
      21
    ],
    "4eae7bc2": [
      21
    ],
    "3c346bc8": [
      21
    ],
    "c31e39ce": [
      21
    ],
    "3e8c5494": [
      10
    ],
    "1391133a": [
      10
    ],
    "8ab411cc": [
      10
    ],
    "51b8b3ce": [
      10
    ],
    "f18e6240": [
      10
    ],
    "448c363c": [
      15
    ],
    "0e31d68b": [
      15
    ],
    "478b01f4": [
      15
    ],
    "11308c1f": [
      15
    ],
    "d5e6df68": [
      15
    ],
    "0cf26144": [
      9
    ],
    "a9849c7c": [
      9
    ],
    "4b2897c3": [
      9
    ],
    "1db8c5bc": [
      9
    ],
    "316e91ba": [
      27
    ],
    "30b61996": [
      27
    ],
    "186d6038": [
      27
    ],
    "6dce8f21": [
      27
    ],
    "ea2f179c": [
      27
    ],
    "6af65f02": [
      44
    ],
    "79df7aa8": [
      44
    ],
    "52b11c00": [
      44
    ],
    "00abec94": [
      44
    ],
    "18793cfa": [
      44
    ],
    "39b9273d": [
      30
    ],
    "5bdf2880": [
      30
    ],
    "716417fb": [
      30
    ],
    "6156cf6c": [
      30
    ],
    "34b03b16": [
      30
    ],
    "244a7924": [
      26
    ],
    "a73728ee": [
      26
    ],
    "6a1f3012": [
      26
    ],
    "01b391c6": [
      26
    ],
    "5d5b2e58": [
      26
    ],
    "9af23748": [
      23
    ],
    "5902ef16": [
      23
    ],
    "de0a1880": [
      23
    ],
    "11a62909": [
      23
    ],
    "5d8dcb86": [
      23
    ],
    "6b6f28a4": [
      34
    ],
    "0268d747": [
      34
    ],
    "13ece008": [
      34
    ],
    "409077db": [
      34
    ],
    "3f009064": [
      34
    ],
    "9870bcd6": [
      43
    ],
    "45731e04": [
      43
    ],
    "2c54540e": [
      43
    ],
    "f8ca82d0": [
      43
    ],
    "932ea482": [
      43
    ],
    "717c2b31": [
      36
    ],
    "58d15bda": [
      36
    ],
    "7d34666f": [
      36
    ],
    "94ad4e74": [
      36
    ],
    "42b7042e": [
      36
    ],
    "3d5e0ddd": [
      3
    ],
    "eb190944": [
      3
    ],
    "0c03fe7e": [
      3
    ],
    "33f0b1f2": [
      3
    ],
    "0e338587": [
      3
    ],
    "1a44b6ec": [
      42
    ],
    "ac80ec24": [
      42
    ],
    "997d9db6": [
      42
    ],
    "765261b4": [
      42
    ],
    "0ca11c31": [
      8
    ],
    "1aafd9fb": [
      8
    ],
    "19d03c95": [
      8
    ],
    "58d77a8f": [
      8
    ],
    "3339d74a": [
      8
    ],
    "dd694f56": [
      5
    ],
    "19775aa6": [
      5
    ],
    "d8d7e75a": [
      5
    ],
    "bf7866dc": [
      5
    ],
    "595c2d4d": [
      5
    ],
    "fca6cb0c": [
      18
    ],
    "0270e438": [
      18
    ],
    "79ed1a15": [
      18
    ],
    "76b4aeb2": [
      18
    ],
    "0dfa969e": [
      20
    ],
    "186897d5": [
      20
    ],
    "372a5545": [
      20
    ],
    "360920ca": [
      20
    ],
    "08d5f799": [
      11
    ],
    "0d2e48f2": [
      11
    ],
    "07db533d": [
      11
    ],
    "4c2aa71b": [
      11
    ],
    "09d15cfa": [
      11
    ],
    "58e3b09e": [
      24,
      39
    ],
    "0a79d274": [
      24,
      39
    ],
    "75279a02": [
      24,
      39
    ],
    "38eab75a": [
      24,
      39
    ],
    "41ba71c8": [
      24,
      39
    ],
    "6b592a68": [
      16
    ],
    "2feb88db": [
      16
    ],
    "e5a07a68": [
      16
    ],
    "57f95522": [
      16
    ],
    "642d16dc": [
      16
    ],
    "5fe96350": [
      22
    ],
    "c633395c": [
      22
    ],
    "40fe2fe6": [
      22
    ],
    "a0716bae": [
      39
    ],
    "3f38fdac": [
      39
    ]
  },
  "assetsMapping": {
    "29558862": [
      "51bf4b4.js"
    ],
    "df3fb4c4": [
      "0dad5a7.js"
    ],
    "400e5050": [
      "13e6946.js"
    ],
    "6fca0322": [
      "161288b.js"
    ],
    "f55af4dc": [
      "1cff849.js"
    ],
    "71a89f0a": [
      "1d20270.js"
    ],
    "b70e7e24": [
      "1d9def6.js"
    ],
    "28f2b3b8": [
      "2bb6025.js"
    ],
    "4e52ab81": [
      "32ec95a.js"
    ],
    "29ca2bae": [
      "3754c56.js"
    ],
    "18bf9ecc": [
      "3a6d18b.js"
    ],
    "59bc0d2d": [
      "3b0361c.js"
    ],
    "97aecab4": [
      "3e10c1d.js"
    ],
    "b70ad3ae": [
      "3f92b4e.js"
    ],
    "587c13d6": [
      "437abfe.js"
    ],
    "e81092fe": [
      "441edb3.js"
    ],
    "085a35c4": [
      "4429295.js"
    ],
    "5813a0f7": [
      "47aa85a.js"
    ],
    "26bac33a": [
      "47d267d.js"
    ],
    "28873d38": [
      "4ae27bd.js"
    ],
    "7691a55e": [
      "4d7dea9.js"
    ],
    "51bae372": [
      "4f18cd2.js"
    ],
    "2a130dde": [
      "57cddbb.js"
    ],
    "2aa49924": [
      "677be11.js"
    ],
    "48459d21": [
      "7470bf5.js"
    ],
    "c194f212": [
      "756caf6.js"
    ],
    "b707bfa6": [
      "769ef96.js"
    ],
    "3f64bfb0": [
      "7c90b3c.js"
    ],
    "72d9f18c": [
      "80c9862.js"
    ],
    "879415c4": [
      "87346c0.js"
    ],
    "1a3ae26b": [
      "8f403d4.js"
    ],
    "7ea24c87": [
      "966c4af.js"
    ],
    "294a37d2": [
      "9866687.js"
    ],
    "b70110a4": [
      "a69b2f3.js"
    ],
    "b7076dd6": [
      "ab74a57.js"
    ],
    "2a60bcba": [
      "c4ffe79.js"
    ],
    "f45ff1a6": [
      "dab7934.js"
    ],
    "d1c42034": [
      "e1c59ab.js"
    ],
    "676b98cc": [
      "f4ff530.js"
    ],
    "29017a06": [
      "f6d9ca7.js"
    ],
    "292104f0": [
      "fea7a24.js"
    ],
    "7abdeabf": [
      "fffdfaa.js"
    ]
  }
}